<?xml version = '1.0' encoding = 'UTF-8'?>
<Relation class="oracle.dbtools.crest.model.design.logical.Relation" name="ME_Module_FK" directorySegmentName="seg_1" id="56A9B451-B647-FC12-B3BB-01535E5A6912">
<createdBy>bisha</createdBy>
<createdTime>2022-03-19 19:03:02 UTC</createdTime>
<generatorID>61F4BE2D-EE97-099C-4E19-031B7E76A023</generatorID>
<ownerDesignName>cw-db</ownerDesignName>
<engineerTo>
<item key="191B4BF2-398F-45F2-D4C0-870FA9FF6E1E" value="true"/>
</engineerTo>
<sourcePk>42CEF1D2-59E5-A289-6729-19E6D1F47F1E</sourcePk>
<identifying>true</identifying>
<optionalSource>true</optionalSource>
<optionalTarget>false</optionalTarget>
<sourceCardinality>1</sourceCardinality>
<sourceEntity>6A85BD88-07C3-BBBA-B719-5494772686A2</sourceEntity>
<targetCardinalityString>*</targetCardinalityString>
<targetEntity>2421ACD7-E795-4712-2BDB-F5B5092F9191</targetEntity>
<transferable>true</transferable>
<deleteRule>NO ACTION</deleteRule>
</Relation>
